MANIFEST.in
README.md
requirements.txt
setup.py
Flask_Monitoring.egg-info/PKG-INFO
Flask_Monitoring.egg-info/SOURCES.txt
Flask_Monitoring.egg-info/dependency_links.txt
Flask_Monitoring.egg-info/entry_points.txt
Flask_Monitoring.egg-info/not-zip-safe
Flask_Monitoring.egg-info/requires.txt
Flask_Monitoring.egg-info/top_level.txt
docs/README.rst
docs/changelog.rst
flask_monitoringdashboard/__init__.py
flask_monitoringdashboard/cli.py
flask_monitoringdashboard/constants.json
flask_monitoringdashboard/main.py
flask_monitoringdashboard/controllers/__init__.py
flask_monitoringdashboard/controllers/endpoints.py
flask_monitoringdashboard/controllers/outliers.py
flask_monitoringdashboard/controllers/profiler.py
flask_monitoringdashboard/controllers/requests.py
flask_monitoringdashboard/controllers/versions.py
flask_monitoringdashboard/core/__init__.py
flask_monitoringdashboard/core/auth.py
flask_monitoringdashboard/core/cache.py
flask_monitoringdashboard/core/colors.py
flask_monitoringdashboard/core/date_interval.py
flask_monitoringdashboard/core/group_by.py
flask_monitoringdashboard/core/logger.py
flask_monitoringdashboard/core/measurement.py
flask_monitoringdashboard/core/rules.py
flask_monitoringdashboard/core/timezone.py
flask_monitoringdashboard/core/utils.py
flask_monitoringdashboard/core/config/__init__.py
flask_monitoringdashboard/core/config/parser.py
flask_monitoringdashboard/core/custom_graph/__init__.py
flask_monitoringdashboard/core/profiler/__init__.py
flask_monitoringdashboard/core/profiler/baseProfiler.py
flask_monitoringdashboard/core/profiler/outlierProfiler.py
flask_monitoringdashboard/core/profiler/performanceProfiler.py
flask_monitoringdashboard/core/profiler/stacktraceProfiler.py
flask_monitoringdashboard/core/profiler/util/__init__.py
flask_monitoringdashboard/core/profiler/util/groupedStackLine.py
flask_monitoringdashboard/core/profiler/util/pathHash.py
flask_monitoringdashboard/core/profiler/util/stringHash.py
flask_monitoringdashboard/core/reporting/__init__.py
flask_monitoringdashboard/core/reporting/mean_permutation_test.py
flask_monitoringdashboard/core/reporting/questions/__init__.py
flask_monitoringdashboard/core/reporting/questions/average_latency.py
flask_monitoringdashboard/core/reporting/questions/report_question.py
