Metadata-Version: 1.2
Name: Flask-Monitoring
Version: 1.1.2
Summary: Automatically monitor the evolving performance of Flask/Python web services.
Home-page: https://github.com/phamngocquy/Flask-MonitoringDashboard
Author: Quy Ngoc Pham
Author-email: phamngocquy97@gmail.com
License: UNKNOWN
Project-URL: PyPi, https://pypi.org/project/Flask-MonitoringDashboard/
Project-URL: Documentation, http://flask-monitoringdashboard.readthedocs.io/
Project-URL: Bug Reports, https://github.com/phamngocquy/Flask-MonitoringDashboard/issues
Project-URL: Source, https://github.com/flask-dashboard/Flask-MonitoringDashboard/
Platform: Any
Classifier: Environment :: Web Environment
Classifier: Intended Audience :: Developers
Classifier: Operating System :: OS Independent
Classifier: License :: OSI Approved :: MIT License
Classifier: Programming Language :: Python
Classifier: Topic :: Software Development :: Libraries :: Python Modules
Classifier: Programming Language :: Python :: 2.7
Classifier: Programming Language :: Python :: 3.5
Classifier: Programming Language :: Python :: 3.6
Classifier: Programming Language :: Python :: 3.7
Classifier: Framework :: Flask
